falcon_deps/__init__.py
falcon_deps/py.typed
falcon_deps/resource.py
falcon_deps-0.1.3.dist-info/METADATA
falcon_deps-0.1.3.dist-info/WHEEL
falcon_deps-0.1.3.dist-info/RECORD
