Metadata-Version: 2.1
Name: falcon-deps
Version: 0.1.3
Summary: 
Author: chandr-andr (Kiselev Aleksandr)
Author-email: chandr@chandr.net
Requires-Python: >=3.9,<4.0
Classifier: Programming Language :: Python :: 3
Classifier: Programming Language :: Python :: 3.9
Classifier: Programming Language :: Python :: 3.10
Classifier: Programming Language :: Python :: 3.11
Classifier: Programming Language :: Python :: 3.12
Classifier: Programming Language :: Python :: 3.13
Requires-Dist: aiohttp (>=3.10.10,<4.0.0)
Requires-Dist: falcon (>=4.0.0,<5.0.0)
Requires-Dist: taskiq-dependencies (>=1.5.4,<2.0.0)
Requires-Dist: uvicorn (>=0.32.0,<0.33.0)
